laiss_lmt.py
laiss_lmt-0.1.0.dist-info/METADATA
laiss_lmt-0.1.0.dist-info/WHEEL
laiss_lmt-0.1.0.dist-info/entry_points.txt
laiss_lmt-0.1.0.dist-info/top_level.txt
laiss_lmt-0.1.0.dist-info/RECORD
