Metadata-Version: 2.1
Name: laiss-lmt
Version: 0.1.0
Summary: Laiss model training for cognitive AI models
Author: Júlio Papel
Author-email: info@juliopapel.pt
Classifier: Programming Language :: Python :: 3
Classifier: License :: OSI Approved :: MIT License
Classifier: Operating System :: OS Independent
Requires-Python: >=3.10
Requires-Dist: argparse
